linkook/__init__.py
linkook/__main__.py
linkook/linkook.py
linkook/outputer/__init__.py
linkook/outputer/console_printer.py
linkook/outputer/result_writer.py
linkook/outputer/visualize_output.py
linkook/provider/__init__.py
linkook/provider/provider.json
linkook/provider/provider.py
linkook/provider/provider_manager.py
linkook/scanner/__init__.py
linkook/scanner/scanner_manager.py
linkook/scanner/site_scanner.py
linkook-1.1.2.dist-info/LICENSE
linkook-1.1.2.dist-info/METADATA
linkook-1.1.2.dist-info/WHEEL
linkook-1.1.2.dist-info/entry_points.txt
linkook-1.1.2.dist-info/top_level.txt
linkook-1.1.2.dist-info/RECORD
